podbox/__init__.py
podbox-0.1.0.dist-info/DESCRIPTION.rst
podbox-0.1.0.dist-info/METADATA
podbox-0.1.0.dist-info/RECORD
podbox-0.1.0.dist-info/WHEEL
podbox-0.1.0.dist-info/metadata.json
podbox-0.1.0.dist-info/top_level.txt
podbox-0.1.0.dist-info/zip-safe
